ppm/__init__.py
ppm/cli.py
ppm/core.py
ingot_ppm-1.1.6.dist-info/METADATA
ingot_ppm-1.1.6.dist-info/WHEEL
ingot_ppm-1.1.6.dist-info/entry_points.txt
ingot_ppm-1.1.6.dist-info/licenses/LICENSE
ingot_ppm-1.1.6.dist-info/RECORD
