Metadata-Version: 2.4
Name: ingot-ppm
Version: 1.1.6
Summary: A faster and more comprehensive Python package manager
Author-email: IngotStudio <xmz_20130612@163.com>
License-Expression: MIT
License-File: LICENSE
Keywords: dependency management,package manager,python
Classifier: Development Status :: 3 - Alpha
Classifier: Intended Audience :: Developers
Classifier: License :: OSI Approved :: MIT License
Classifier: Programming Language :: Python :: 3
Classifier: Programming Language :: Python :: 3.7
Classifier: Programming Language :: Python :: 3.8
Classifier: Programming Language :: Python :: 3.9
Classifier: Programming Language :: Python :: 3.10
Classifier: Topic :: Software Development :: Build Tools
Requires-Python: >=3.7
Requires-Dist: aiohttp>=3.8.0
Requires-Dist: click>=8.0.0
Requires-Dist: packaging>=21.0
Requires-Dist: rich>=10.0.0
Requires-Dist: tomli>=2.0.0
